README.rst
setup.cfg
setup.py
geo/__init__.py
geo/locator.py
test_suraj_mygmap.egg-info/PKG-INFO
test_suraj_mygmap.egg-info/SOURCES.txt
test_suraj_mygmap.egg-info/dependency_links.txt
test_suraj_mygmap.egg-info/requires.txt
test_suraj_mygmap.egg-info/top_level.txt