Metadata-Version: 1.1
Name: test-suraj-mygmap
Version: 0.0.5
Summary: A small wrapper around google maps api
Home-page: https://github.com/nikhilkumarsingh/mygmap
Author: Suraj Gaire, Niraj Gaire
Author-email: surajgaire0@gmail.com
License: MIT
Keywords: maps location address
Platform: UNKNOWN
Classifier: Development Status :: 1 - Planning
Classifier: Intended Audience :: Developers
Classifier: Topic :: Internet
Classifier: License :: OSI Approved :: MIT License
Classifier: Programming Language :: Python
Classifier: Programming Language :: Python :: 3
Classifier: Programming Language :: Python :: 3.8
Classifier: Programming Language :: Python :: 3.9
Classifier: Programming Language :: Python :: 3.10
